pyssdb.py
pyssdb-0.4.2.dist-info/METADATA
pyssdb-0.4.2.dist-info/RECORD
pyssdb-0.4.2.dist-info/WHEEL
pyssdb-0.4.2.dist-info/top_level.txt
