Metadata-Version: 2.1
Name: pyssdb
Version: 0.4.2
Summary: A SSDB Client Library for Python.
Home-page: https://github.com/ifduyue/pyssdb
Author: Yue Du
Author-email: ifduyue@gmail.com
License: BSD
Keywords: ssdb
Platform: UNKNOWN
Classifier: Development Status :: 4 - Beta
Classifier: Programming Language :: Python
Classifier: Programming Language :: Python :: 2.6
Classifier: Programming Language :: Python :: 2.7
Classifier: Programming Language :: Python :: 3.5
Classifier: Programming Language :: Python :: 3.6
Classifier: Programming Language :: Python :: 3.7
Classifier: Intended Audience :: Developers
Classifier: License :: OSI Approved :: BSD License
Classifier: Operating System :: POSIX
Classifier: Operating System :: POSIX :: Linux
Classifier: Topic :: Software Development :: Libraries :: Python Modules
